{
    "token_0": {
        "fetched_at": "2025-10-15 20:30:07 UTC",
        "ok": true,
        "http_code": 200,
        "token": "hdnea=exp=1760516382~acl=/*~id=12079153333261060838868375648447~hmac=38b2b511a19f5c6947a89fb236984673551b37139f66f2a1b879ed3b02dc4a89",
        "expiry_unix": 1760516382,
        "expiry_human": "2025-10-15 08:19:42 UTC"
    },
    "token_1": {
        "fetched_at": "2025-10-15 20:30:07 UTC",
        "ok": true,
        "http_code": 200,
        "token": "hdnea=exp=1760574603~acl=/*~id=46981014830828884401062358057099~hmac=15ea45a5fe97ed9c1fc658b567d302ea05e20cfd8276224ee7a32b53e4d5538d",
        "expiry_unix": 1760574603,
        "expiry_human": "2025-10-16 00:30:03 UTC"
    },
    "token_2": {
        "fetched_at": "2025-10-15 20:30:09 UTC",
        "ok": true,
        "http_code": 200,
        "token": "hdnea=exp=1760574603~acl=/*~id=46981014830828884401062358057099~hmac=15ea45a5fe97ed9c1fc658b567d302ea05e20cfd8276224ee7a32b53e4d5538d",
        "expiry_unix": 1760574603,
        "expiry_human": "2025-10-16 00:30:03 UTC"
    },
    "token_3": {
        "fetched_at": "2025-10-15 20:30:11 UTC",
        "ok": true,
        "http_code": 200,
        "token": "hdnea=exp=1760596203~acl=/*~id=66461536600757710046622352462624~hmac=bec6a3d1f1551a807105a559c47dab8d3b0c1343d35bf5f56d6ea06e5c3e2af7",
        "expiry_unix": 1760596203,
        "expiry_human": "2025-10-16 06:30:03 UTC"
    }
}